{
    "Realty Income Corporation":"US7561091049",
    "British American Tobacco":"GB0002875804",
    "Core MSCI World":"IE00B4L5Y983",
    "MSCI China (Acc)":"IE00BJ5JPG56",
    "Automation & Robotics":"IE00BYZK4552",
    "MDAX EUR (Acc)":"DE0005933923",
    "Core MSCI World USD (Acc)": "IE00B4L5Y983",
    "Deutsche Pfandbriefbank": "DE0008019001",
    "Gladstone Commercial": "US3765361080",
    "Global Clean Energy": "IE00B1XNHC34",
    "Global Clean Energy USD (Dist)": "IE00B1XNHC34",
    "MSCI World USD (Dist)": "IE00B0M62Q58",
    "MSCI World": "IE00B0M62Q58",
    "Main Street Capital": "US56035L1044",
    "Main Street Capital Corp.": "US56035L1044",
    "Omega Healthcare Investors": "US6819361006",
    "Omega Healthcare Invs": "US6819361006",
    "Orion Office REIT Inc.": "US68629Y1038",
    "Realty Income": "US7561091049",
    "STOXX Global Dividend 100 EUR (Dist)": "DE000A0F5UH1",
    "STOXX Global Select Dividend 100": "DE000A0F5UH1",
    "TSMC (ADR)": "US8740391003",
    "Texas Instruments": "US8825081040",
    "Warner Bros Discovery": "US9344231041",
    "McDonald's": "US5801351017",
    "Rio Tinto": "GB0007188757",
    "Visa": "US92826C8394",
    "PepsiCo": "US7134481081",
    "Pepsico": "US7134481081",
    "BASF": "DE000BASF111",
    "Deutsche Post": "DE0005552004",
    "SAP": "DE0007164600" ,
    "Shell": "GB00BP6MXD84", 
    "Deutsche Telekom": "DE0005557508",
    "Unilever": "GB00B10RZP78",
    "Royal Dutch Shell (A)": "GB00BP6MXD84",
    "Gazprom (ADR)": "US3682872078",
    "Gazprom": "US3682872078"
}
